parasol/.coverage
parasol/CarpetPlot.py
parasol/Excel_wrapper.py
parasol/Goal.py
parasol/HTML_supt.py
parasol/LikeDict.py
parasol/LikeDict.py.bak
parasol/Optimize.py
parasol/PPT_wrapper.py
parasol/Plots.py
parasol/Plots_Cache.py
parasol/Summary.py
parasol/Word_wrapper.py
parasol/__init__.py
parasol/_version.py
parasol/cast.py
parasol/coverage.xml
parasol/excel_const.py
parasol/htm
parasol/make_zip.py
parasol/parameters.py
parasol/parasol_main.py
parasol/xlChFormula.py
parasol/examples/box.doc
parasol/examples/box.htm
parasol/examples/box.ppt
parasol/examples/box.py
parasol/examples/box.xlsx
parasol/examples/box2.htm
parasol/examples/box2.py
parasol/examples/box2box2.summary
parasol/examples/boxbox.summary
parasol/examples/escher01.gif
parasol/examples/fold_card.htm
parasol/examples/fold_card.py
parasol/examples/fold_card_feas.htm
parasol/examples/fold_card_feas.py
parasol/examples/fold_card_feasfold_card_feas.summary
parasol/examples/fold_cardfold_card.summary
parasol/examples/func_opt_a.htm
parasol/examples/func_opt_a.py
parasol/examples/func_opt_afunc_opt_a.summary
parasol/examples/func_opt_b.htm
parasol/examples/func_opt_b.py
parasol/examples/func_opt_bfunc_opt_b.summary
parasol/examples/irobot2.gif
parasol/examples/box/box_1__sens_sysMass_vs_L.csv
parasol/examples/box/box_1__sens_sysMass_vs_L_W_h.png
parasol/examples/box/box_1__sens_sysMass_vs_W.csv
parasol/examples/box/box_1__sens_sysMass_vs_h.csv
parasol/examples/box/box_2__sens_Volume_vs_L.csv
parasol/examples/box/box_2__sens_Volume_vs_L_W_h.png
parasol/examples/box/box_2__sens_Volume_vs_W.csv
parasol/examples/box/box_2__sens_Volume_vs_h.csv
parasol/examples/box/box_3___carpet_Volume_vs_h_L_sysMass.png
parasol/examples/box/box_4___Volume_vs_W_h.png
parasol/examples/box/box_5___sysMass_vs_W_h.png
parasol/examples/box/box_6___param_Volume_vs_h.png
parasol/examples/box/box_6__param_Volume_vs_h.csv
parasol/examples/box/box_7___Volume_vs_L.csv
parasol/examples/box/box_7___Volume_vs_L.png
parasol-0.2.1.dist-info/AUTHORS.rst
parasol-0.2.1.dist-info/LICENSE
parasol-0.2.1.dist-info/LICENSE.txt
parasol-0.2.1.dist-info/METADATA
parasol-0.2.1.dist-info/WHEEL
parasol-0.2.1.dist-info/top_level.txt
parasol-0.2.1.dist-info/RECORD
