Metadata-Version: 2.1
Name: parasol
Version: 0.2.1
Summary: ParaSol (Parametric Solutions) is a python framework in which mathematical models can be investigated parametrically.
Home-page: http://parasol.readthedocs.org/en/latest/
Download-URL: https://github.com/sonofeft/ParaSol
Author: Charlie Taylor
Author-email: Charlie Taylor <cet@appliedpython.com>
License: GPL-3
Project-URL: Homepage, http://parasol.readthedocs.org/en/latest/
Project-URL: Bug Tracker, https://github.com/sonofeft/ParaSol
Keywords: parasol setuptools development
Platform: any
Classifier: Programming Language :: Python :: 3
Classifier: License :: OSI Approved :: GNU General Public License v3 (GPLv3)
Classifier: Operating System :: OS Independent
Requires-Python: >=3.7
License-File: LICENSE
License-File: LICENSE.txt
License-File: AUTHORS.rst
Requires-Dist: matplotlib
Requires-Dist: scipy
Requires-Dist: pillow
Provides-Extra: dev
Requires-Dist: check-manifest ; extra == 'dev'
Provides-Extra: test
Requires-Dist: coverage ; extra == 'test'
